encoding_mcp/__init__.py
encoding_mcp/__main__.py
encoding_mcp/encoding_detector.py
encoding_mcp/file_operations.py
encoding_mcp/server.py
encoding_mcp-1.0.0.dist-info/licenses/LICENSE
encoding_mcp-1.0.0.dist-info/METADATA
encoding_mcp-1.0.0.dist-info/WHEEL
encoding_mcp-1.0.0.dist-info/entry_points.txt
encoding_mcp-1.0.0.dist-info/top_level.txt
encoding_mcp-1.0.0.dist-info/RECORD
