Metadata-Version: 2.4
Name: encoding-mcp
Version: 1.0.0
Summary: Windows 빌드 환경에서 필요한 UTF-8 with BOM 인코딩 파일을 생성하고 관리하는 MCP 서버
Home-page: https://github.com/whyjp/encoding_mcp
Author: Encoding MCP Team
Author-email: Encoding MCP Team <whyj.park@gmail.com>
Maintainer-email: Encoding MCP Team <whyj.park@gmail.com>
License-Expression: MIT
Project-URL: Homepage, https://github.com/whyjp/encoding_mcp
Project-URL: Documentation, https://github.com/whyjp/encoding_mcp#readme
Project-URL: Repository, https://github.com/whyjp/encoding_mcp.git
Project-URL: Bug Tracker, https://github.com/whyjp/encoding_mcp/issues
Project-URL: Changelog, https://github.com/whyjp/encoding_mcp/releases
Keywords: mcp,encoding,utf8,bom,windows,build,cpp,powershell
Classifier: Development Status :: 5 - Production/Stable
Classifier: Intended Audience :: Developers
Classifier: Topic :: Software Development :: Build Tools
Classifier: Topic :: Text Processing :: Markup
Classifier: Programming Language :: Python :: 3
Classifier: Programming Language :: Python :: 3.10
Classifier: Programming Language :: Python :: 3.11
Classifier: Programming Language :: Python :: 3.12
Classifier: Operating System :: OS Independent
Requires-Python: >=3.10
License-File: LICENSE
Requires-Dist: mcp>=1.0.0
Requires-Dist: charset-normalizer>=3.0.0
Requires-Dist: chardet>=5.0.0
Provides-Extra: dev
Requires-Dist: pytest>=7.0.0; extra == "dev"
Requires-Dist: pytest-cov>=4.0.0; extra == "dev"
Requires-Dist: black>=23.0.0; extra == "dev"
Requires-Dist: flake8>=6.0.0; extra == "dev"
Requires-Dist: mypy>=1.0.0; extra == "dev"
Requires-Dist: build>=0.10.0; extra == "dev"
Requires-Dist: twine>=4.0.0; extra == "dev"
Provides-Extra: test
Requires-Dist: pytest>=7.0.0; extra == "test"
Requires-Dist: pytest-cov>=4.0.0; extra == "test"
Dynamic: author
Dynamic: home-page
Dynamic: license-file
Dynamic: requires-python
